<DeployManagerInst>
    <prototypes>
        <val>Sink_HLW</val>
        <val>ANO-1</val>
        <val>ANO-2</val>
        <val>BEAVER_VALLEY-1</val>
        <val>BEAVER_VALLEY-2</val>
        <val>BRAIDWOOD-1</val>
        <val>BRAIDWOOD-2</val>
        <val>BROWNS_FERRY-1</val>
        <val>BROWNS_FERRY-2</val>
        <val>BROWNS_FERRY-3</val>
        <val>BRUNSWICK-1</val>
        <val>BRUNSWICK-2</val>
        <val>BYRON-1</val>
        <val>BYRON-2</val>
        <val>CALLAWAY-1</val>
        <val>CALVERT_CLIFFS-1</val>
        <val>CALVERT_CLIFFS-2</val>
        <val>CATAWBA-1</val>
        <val>CATAWBA-2</val>
        <val>CLINTON-1</val>
        <val>COLUMBIA</val>
        <val>COMANCHE_PEAK-1</val>
        <val>COMANCHE_PEAK-2</val>
        <val>COOK-1</val>
        <val>COOK-2</val>
        <val>COOPER</val>
        <val>CRYSTAL_RIVER-3</val>
        <val>DAVIS_BESSE-1</val>
        <val>DIABLO_CANYON-1</val>
        <val>DIABLO_CANYON-2</val>
        <val>DRESDEN-2</val>
        <val>DRESDEN-3</val>
        <val>DUANE_ARNOLD-1</val>
        <val>FARLEY-1</val>
        <val>FARLEY-2</val>
        <val>FERMI-2</val>
        <val>FITZPATRICK</val>
        <val>FORT_CALHOUN-1</val>
        <val>GINNA</val>
        <val>GRAND_GULF-1</val>
        <val>HADDAM_NECK</val>
        <val>HARRIS-1</val>
        <val>HATCH-1</val>
        <val>HATCH-2</val>
        <val>HOPE_CREEK-1</val>
        <val>INDIAN_POINT-2</val>
        <val>INDIAN_POINT-3</val>
        <val>KEWAUNEE</val>
        <val>LASALLE-1</val>
        <val>LASALLE-2</val>
        <val>LIMERICK-1</val>
        <val>LIMERICK-2</val>
        <val>MAINE_YANKEE</val>
        <val>MCGUIRE-1</val>
        <val>MCGUIRE-2</val>
        <val>MILLSTONE-1</val>
        <val>MILLSTONE-2</val>
        <val>MILLSTONE-3</val>
        <val>MONTICELLO</val>
        <val>NINE_MILE_POINT-1</val>
        <val>NINE_MILE_POINT-2</val>
        <val>NORTH_ANNA-1</val>
        <val>NORTH_ANNA-2</val>
        <val>OCONEE-1</val>
        <val>OCONEE-2</val>
        <val>OCONEE-3</val>
        <val>OYSTER_CREEK</val>
        <val>PALISADES</val>
        <val>PALO_VERDE-1</val>
        <val>PALO_VERDE-2</val>
        <val>PALO_VERDE-3</val>
        <val>PEACH_BOTTOM-2</val>
        <val>PEACH_BOTTOM-3</val>
        <val>PERRY-1</val>
        <val>PILGRIM-1</val>
        <val>POINT_BEACH-1</val>
        <val>POINT_BEACH-2</val>
        <val>PRAIRIE_ISLAND-1</val>
        <val>PRAIRIE_ISLAND-2</val>
        <val>QUAD_CITIES-1</val>
        <val>QUAD_CITIES-2</val>
        <val>RANCHO_SECO-1</val>
        <val>RIVER_BEND-1</val>
        <val>ROBINSON-2</val>
        <val>SALEM-1</val>
        <val>SALEM-2</val>
        <val>SAN_ONOFRE-1</val>
        <val>SAN_ONOFRE-2</val>
        <val>SAN_ONOFRE-3</val>
        <val>SEABROOK-1</val>
        <val>SEQUOYAH-1</val>
        <val>SEQUOYAH-2</val>
        <val>SHOREHAM</val>
        <val>SOUTH_TEXAS-1</val>
        <val>SOUTH_TEXAS-2</val>
        <val>ST._LUCIE-1</val>
        <val>ST._LUCIE-2</val>
        <val>SUMMER-1</val>
        <val>SURRY-1</val>
        <val>SURRY-2</val>
        <val>SUSQUEHANNA-1</val>
        <val>SUSQUEHANNA-2</val>
        <val>THREE_MILE_ISLAND-1</val>
        <val>THREE_MILE_ISLAND-2</val>
        <val>TROJAN</val>
        <val>TURKEY_POINT-3</val>
        <val>TURKEY_POINT-4</val>
        <val>VERMONT_YANKEE</val>
        <val>VOGTLE-1</val>
        <val>VOGTLE-2</val>
        <val>WATERFORD-3</val>
        <val>WATTS_BAR-1</val>
        <val>WATTS_BAR-2</val>
        <val>WOLF_CREEK</val>
        <val>ZION-1</val>
        <val>ZION-2</val>
    </prototypes>
    <build_times>
        <val>900</val>
        <val>117</val>
        <val>169</val>
        <val>138</val>
        <val>273</val>
        <val>271</val>
        <val>282</val>
        <val>106</val>
        <val>117</val>
        <val>141</val>
        <val>144</val>
        <val>125</val>
        <val>243</val>
        <val>266</val>
        <val>239</val>
        <val>121</val>
        <val>144</val>
        <val>242</val>
        <val>258</val>
        <val>269</val>
        <val>234</val>
        <val>305</val>
        <val>340</val>
        <val>122</val>
        <val>160</val>
        <val>113</val>
        <val>146</val>
        <val>153</val>
        <val>239</val>
        <val>251</val>
        <val>64</val>
        <val>80</val>
        <val>114</val>
        <val>153</val>
        <val>198</val>
        <val>262</val>
        <val>122</val>
        <val>105</val>
        <val>60</val>
        <val>239</val>
        <val>32</val>
        <val>266</val>
        <val>119</val>
        <val>166</val>
        <val>260</val>
        <val>103</val>
        <val>137</val>
        <val>112</val>
        <val>213</val>
        <val>233</val>
        <val>244</val>
        <val>297</val>
        <val>95</val>
        <val>201</val>
        <val>222</val>
        <val>72</val>
        <val>131</val>
        <val>254</val>
        <val>75</val>
        <val>59</val>
        <val>272</val>
        <val>161</val>
        <val>189</val>
        <val>101</val>
        <val>108</val>
        <val>118</val>
        <val>58</val>
        <val>85</val>
        <val>246</val>
        <val>258</val>
        <val>276</val>
        <val>111</val>
        <val>117</val>
        <val>265</val>
        <val>92</val>
        <val>71</val>
        <val>92</val>
        <val>108</val>
        <val>121</val>
        <val>88</val>
        <val>90</val>
        <val>118</val>
        <val>252</val>
        <val>70</val>
        <val>145</val>
        <val>198</val>
        <val>32</val>
        <val>214</val>
        <val>226</val>
        <val>306</val>
        <val>188</val>
        <val>205</val>
        <val>260</val>
        <val>280</val>
        <val>292</val>
        <val>137</val>
        <val>222</val>
        <val>216</val>
        <val>91</val>
        <val>99</val>
        <val>216</val>
        <val>235</val>
        <val>115</val>
        <val>161</val>
        <val>133</val>
        <val>95</val>
        <val>103</val>
        <val>94</val>
        <val>268</val>
        <val>292</val>
        <val>244</val>
        <val>374</val>
        <val>618</val>
        <val>246</val>
        <val>103</val>
        <val>109</val>
    </build_times>
    <n_build>
        <val>1</val>
        <val>1</val>
        <val>1</val>
        <val>1</val>
        <val>1</val>
        <val>1</val>
        <val>1</val>
        <val>1</val>
        <val>1</val>
        <val>1</val>
        <val>1</val>
        <val>1</val>
        <val>1</val>
        <val>1</val>
        <val>1</val>
        <val>1</val>
        <val>1</val>
        <val>1</val>
        <val>1</val>
        <val>1</val>
        <val>1</val>
        <val>1</val>
        <val>1</val>
        <val>1</val>
        <val>1</val>
        <val>1</val>
        <val>1</val>
        <val>1</val>
        <val>1</val>
        <val>1</val>
        <val>1</val>
        <val>1</val>
        <val>1</val>
        <val>1</val>
        <val>1</val>
        <val>1</val>
        <val>1</val>
        <val>1</val>
        <val>1</val>
        <val>1</val>
        <val>1</val>
        <val>1</val>
        <val>1</val>
        <val>1</val>
        <val>1</val>
        <val>1</val>
        <val>1</val>
        <val>1</val>
        <val>1</val>
        <val>1</val>
        <val>1</val>
        <val>1</val>
        <val>1</val>
        <val>1</val>
        <val>1</val>
        <val>1</val>
        <val>1</val>
        <val>1</val>
        <val>1</val>
        <val>1</val>
        <val>1</val>
        <val>1</val>
        <val>1</val>
        <val>1</val>
        <val>1</val>
        <val>1</val>
        <val>1</val>
        <val>1</val>
        <val>1</val>
        <val>1</val>
        <val>1</val>
        <val>1</val>
        <val>1</val>
        <val>1</val>
        <val>1</val>
        <val>1</val>
        <val>1</val>
        <val>1</val>
        <val>1</val>
        <val>1</val>
        <val>1</val>
        <val>1</val>
        <val>1</val>
        <val>1</val>
        <val>1</val>
        <val>1</val>
        <val>1</val>
        <val>1</val>
        <val>1</val>
        <val>1</val>
        <val>1</val>
        <val>1</val>
        <val>1</val>
        <val>1</val>
        <val>1</val>
        <val>1</val>
        <val>1</val>
        <val>1</val>
        <val>1</val>
        <val>1</val>
        <val>1</val>
        <val>1</val>
        <val>1</val>
        <val>1</val>
        <val>1</val>
        <val>1</val>
        <val>1</val>
        <val>1</val>
        <val>1</val>
        <val>1</val>
        <val>1</val>
        <val>1</val>
        <val>1</val>
        <val>1</val>
        <val>1</val>
        <val>1</val>
    </n_build>
</DeployManagerInst>
